slack_error_notification/__init__.py
slack_error_notification/main.py
slack_error_notification/slack_error_notification.py
slack_error_notification-0.1.2.dist-info/LICENSE
slack_error_notification-0.1.2.dist-info/METADATA
slack_error_notification-0.1.2.dist-info/WHEEL
slack_error_notification-0.1.2.dist-info/top_level.txt
slack_error_notification-0.1.2.dist-info/RECORD
