Metadata-Version: 2.1
Name: slack-error-notification
Version: 0.1.2
Summary: A Slack notification handler that send error messages to a Slack channel
Home-page: 
Author: Gordon Oh
Author-email: gordonoh@yahoo.com.sg
License: BSD 2-clause
Classifier: Development Status :: 1 - Planning
Classifier: Intended Audience :: Science/Research
Classifier: License :: OSI Approved :: BSD License
Classifier: Operating System :: POSIX :: Linux
Classifier: Programming Language :: Python :: 2
Classifier: Programming Language :: Python :: 2.7
Classifier: Programming Language :: Python :: 3
Classifier: Programming Language :: Python :: 3.4
Classifier: Programming Language :: Python :: 3.5
License-File: LICENSE
Requires-Dist: slack-sdk
Requires-Dist: Flask (>=2.0.1)
Requires-Dist: Flask-Log-Request-ID
